fuzzy_table_extractor/__init__.py
fuzzy_table_extractor/extractor.py
fuzzy_table_extractor/handlers/__init__.py
fuzzy_table_extractor/handlers/base_handler.py
fuzzy_table_extractor/handlers/docx_handler.py
fuzzy_table_extractor/tests/__init__.py
fuzzy_table_extractor/tests/docx_extraction_test.py
fuzzy_table_extractor/tests/docx_handler_test.py
fuzzy_table_extractor/util.py
fuzzy_table_extractor-0.2.2.dist-info/LICENSE
fuzzy_table_extractor-0.2.2.dist-info/WHEEL
fuzzy_table_extractor-0.2.2.dist-info/METADATA
fuzzy_table_extractor-0.2.2.dist-info/RECORD
