Metadata-Version: 2.1
Name: fuzzy-table-extractor
Version: 0.2.2
Summary: A tool to extract tables from documents using fuzzy matching
Home-page: https://github.com/LeonardoSirino/FuzzyTableExtractor
License: MIT
Author: Leonardo Sirino
Author-email: leonardosirino@outlook.com
Requires-Python: >=3.9,<4.0
Classifier: License :: OSI Approved :: MIT License
Classifier: Programming Language :: Python :: 3
Classifier: Programming Language :: Python :: 3.10
Classifier: Programming Language :: Python :: 3.9
Requires-Dist: Unidecode (>=1.3.2,<2.0.0)
Requires-Dist: fuzzywuzzy (>=0.18.0,<0.19.0)
Requires-Dist: pandas (>=1.3.5,<2.0.0)
Requires-Dist: python-docx (>=0.8.11,<0.9.0)
Requires-Dist: pywin32 (>=303,<304)
